rpcdataloader/__init__.py
rpcdataloader/dataloader.py
rpcdataloader/launch.py
rpcdataloader/rpc.py
rpcdataloader/utils.py
rpcdataloader-0.2.1.dist-info/LICENSE.txt
rpcdataloader-0.2.1.dist-info/METADATA
rpcdataloader-0.2.1.dist-info/WHEEL
rpcdataloader-0.2.1.dist-info/top_level.txt
rpcdataloader-0.2.1.dist-info/RECORD
