Metadata-Version: 2.1
Name: rpcdataloader
Version: 0.2.1
Summary: A Dataloader using rpc-based workers
Author-email: Nicolas Granger <nicolas.granger@cea.fr>
License: CECILL-C
Project-URL: repository, https://github.com/CEA-LIST/RPCDataloader
Project-URL: documentation, https://cea-list.github.io/RPCDataloader
Classifier: License :: CeCILL-C Free Software License Agreement (CECILL-C)
Classifier: Development Status :: 4 - Beta
Classifier: Topic :: Scientific/Engineering
Classifier: Topic :: Software Development :: Libraries :: Python Modules
Requires-Python: >=3.7
License-File: LICENSE.txt
Requires-Dist: tblib
Requires-Dist: torch
Requires-Dist: numpy
Requires-Dist: pickle5 ; python_version < "3.8"
Requires-Dist: typing ; python_version < "3.9"
Provides-Extra: doc
Requires-Dist: sphinx ; extra == 'doc'
Requires-Dist: docutils (>=0.17) ; extra == 'doc'
Requires-Dist: sphinx-rtd-theme (>=1.0) ; extra == 'doc'
Requires-Dist: sphinxext-opengraph ; extra == 'doc'
Requires-Dist: sphinx-copybutton ; extra == 'doc'
Requires-Dist: sphinx-sitemap ; extra == 'doc'
Provides-Extra: test
Requires-Dist: pytest ; extra == 'test'
